molar/__init__.py
molar/client.py
molar/client_config.py
molar/config.py
molar/exceptions.py
molar/install.py
molar/sql_utils.py
molar/backend/__init__.py
molar/backend/alembic_utils.py
molar/backend/main.py
molar/backend/utils.py
molar/backend/api/__init__.py
molar/backend/api/deps.py
molar/backend/api/api_v1/__init__.py
molar/backend/api/api_v1/api.py
molar/backend/api/api_v1/endpoints/__init__.py
molar/backend/api/api_v1/endpoints/alembic.py
molar/backend/api/api_v1/endpoints/database.py
molar/backend/api/api_v1/endpoints/eventstore.py
molar/backend/api/api_v1/endpoints/login.py
molar/backend/api/api_v1/endpoints/query.py
molar/backend/api/api_v1/endpoints/user.py
molar/backend/api/api_v1/endpoints/utils.py
molar/backend/core/__init__.py
molar/backend/core/celery_app.py
molar/backend/core/config.py
molar/backend/core/security.py
molar/backend/crud/__init__.py
molar/backend/crud/base.py
molar/backend/crud/crud_eventstore.py
molar/backend/crud/crud_interface.py
molar/backend/crud/crud_molar_database.py
molar/backend/crud/crud_user.py
molar/backend/database/__init__.py
molar/backend/database/database_handler.py
molar/backend/database/models.py
molar/backend/database/query.py
molar/backend/database/utils.py
molar/backend/email-templates/src/new_account.mjml
molar/backend/email-templates/src/new_database.mjml
molar/backend/email-templates/src/reset_password.mjml
molar/backend/email-templates/src/test_email.mjml
molar/backend/models/__init__.py
molar/backend/models/reflected_models.py
molar/backend/models/user.py
molar/backend/schemas/__init__.py
molar/backend/schemas/database.py
molar/backend/schemas/eventstore.py
molar/backend/schemas/msg.py
molar/backend/schemas/query.py
molar/backend/schemas/revision.py
molar/backend/schemas/token.py
molar/backend/schemas/user.py
molar/cli/__init__.py
molar/cli/alembic_utils.py
molar/cli/cli.py
molar/cli/cli_utils.py
molar/cli/sql_utils.py
molar/cli/commands/__init__.py
molar/cli/commands/cmd_add.py
molar-0.4.5.dist-info/LICENSE
molar-0.4.5.dist-info/METADATA
molar-0.4.5.dist-info/WHEEL
molar-0.4.5.dist-info/entry_points.txt
molar-0.4.5.dist-info/top_level.txt
molar-0.4.5.dist-info/RECORD
