Metadata-Version: 2.1
Name: molar
Version: 0.4.5
Summary: "A database to store chemical data"
Home-page: https://github.com/aspuru-guzik-group/molar
Author: "Theophile Gaudin", "Ian Benlolo", "Zheng Yu Cui"
Author-email: "theophile.gaudin@gmail.com"
License: MIT
Keywords: chemistry,molecule,synthesis,database,postgres,rest,api
Platform: UNKNOWN
Classifier: Programming Language :: Python :: 3.7
Classifier: Programming Language :: Python :: 3.8
Classifier: Programming Language :: Python :: 3.9
License-File: LICENSE
Requires-Dist: Click (>=7.0)
Requires-Dist: rich (>=10.1.0)
Requires-Dist: numpy (>=1.20.1)
Requires-Dist: pandas (>=1.2.3)
Requires-Dist: python-jose[cryptography] (>=3.2.0)
Requires-Dist: pydantic[email] (>=1.8.2)
Requires-Dist: fastapi (>=0.72.0)
Requires-Dist: requests (>=2.28.2)
Provides-Extra: backend
Requires-Dist: alembic (>=1.6.3) ; extra == 'backend'
Requires-Dist: docker-compose (>=1.29.2) ; extra == 'backend'
Requires-Dist: emails (>=0.6) ; extra == 'backend'
Requires-Dist: python-multipart (>=0.0.5) ; extra == 'backend'
Requires-Dist: pytz (>=2019.3) ; extra == 'backend'
Requires-Dist: psycopg2-binary (>=2.8.6) ; extra == 'backend'
Requires-Dist: passlib (>=1.7.4) ; extra == 'backend'
Requires-Dist: SQLAlchemy (>=1.4.15) ; extra == 'backend'
Requires-Dist: bcrypt (>=3.2.0) ; extra == 'backend'
Requires-Dist: uvicorn (>=0.13.4) ; extra == 'backend'
Requires-Dist: python-on-whales (>=0.19.1) ; extra == 'backend'
Requires-Dist: python-dotenv (>=0.17.1) ; extra == 'backend'
Requires-Dist: jinja2 (>=3.0.1) ; extra == 'backend'
Provides-Extra: docs
Requires-Dist: sphinx (~=3.0) ; extra == 'docs'
Requires-Dist: nbsphinx (>=0.8.6) ; extra == 'docs'
Requires-Dist: furo (>=2021.4.11b34) ; extra == 'docs'
Requires-Dist: sphinx-copybutton (>=0.3.3) ; extra == 'docs'
Provides-Extra: tests
Requires-Dist: pytest ; extra == 'tests'
